{
  "version": 1,
  "rules": {
    "investment_bank_rating_target_direct_holding": {
      "enabled": true,
      "priority": 100,
      "allowed_banks": [],
      "extra_keywords": []
    },
    "investment_bank_portfolio_relation": {
      "enabled": false,
      "priority": 95,
      "allowed_banks": [],
      "max_relation_matches": 3
    },
    "holding_keyword_immediate_alert": {
      "enabled": true,
      "priority": 98
    },
    "international_bank_theme_strategy": {
      "enabled": true,
      "priority": 90,
      "allowed_banks": [],
      "extra_theme_keywords": [],
      "extra_action_keywords": [],
      "extra_rotation_theme_aliases": [],
      "allow_broad_style_rotation": true,
      "require_investment_universe_leg": true,
      "min_evidence_score": 2,
      "allow_secondary_sources": true,
      "dedup_lookback_days": 14
    },
    "international_bank_fed_rate_path_revision": {
      "enabled": true,
      "priority": 92,
      "allowed_banks": []
    },
    "direct_holding_hard_variable": {
      "enabled": true,
      "priority": 80,
      "extra_keywords": []
    },
    "official_company_hard_variable": {
      "enabled": true,
      "priority": 70,
      "extra_keywords": [],
      "extra_sources": []
    },
    "macro_policy_line": {
      "enabled": true,
      "priority": 60,
      "extra_primary_keywords": [],
      "extra_secondary_keywords": []
    },
    "trade_friction_escalation": {
      "enabled": true,
      "priority": 65
    },
    "attributed_research_hard_variable": {
      "enabled": true,
      "trusted_institutions": ["semianalysis", "trendforce", "semi", "digitimes", "the_elec", "nikkei_xtech"],
      "extra_aliases": []
    },
    "industry_quantified_hardline": {
      "enabled": true,
      "extra_keywords": []
    }
  }
}
